str_to_ascii/__init__.py
str_to_ascii/str_to_ascii.py
str_to_ascii-1.0.3.dist-info/WHEEL
str_to_ascii-1.0.3.dist-info/METADATA
str_to_ascii-1.0.3.dist-info/RECORD
