Metadata-Version: 1.2
Name: str_to_ascii
Version: 1.0.3
Summary: Simple function for returning only ASCII printable* character string from input string. *and TAB
Home-page: https://github.com/cw-andrews/asciify
License: UNKNOWN
Author: cw-andrews
Author-email: cwandrews.oh@gmail.com
Classifier: License :: OSI Approved :: MIT License
